perl_binary_packing/__init__.py
perl_binary_packing/factory.py
perl_binary_packing/formats.py
perl_binary_packing/tests/__init__.py
perl_binary_packing/tests/base.py
perl_binary_packing/tests/test_binary.py
perl_binary_packing/tests/test_final.py
perl_binary_packing/tests/test_strings.py
perl_binary_packing-0.4.0.dist-info/LICENSE
perl_binary_packing-0.4.0.dist-info/METADATA
perl_binary_packing-0.4.0.dist-info/WHEEL
perl_binary_packing-0.4.0.dist-info/top_level.txt
perl_binary_packing-0.4.0.dist-info/RECORD
