Metadata-Version: 2.2
Name: perl_binary_packing
Version: 0.4.0
Summary: Binary pack/unpack with perl-style format
Author-email: "Mikhail Belov(mishka251)" <mishkabelka251@gmail.com>
Project-URL: Homepage, https://github.com/mishka251/perl_binary_packing
Classifier: Development Status :: 4 - Beta
Classifier: Programming Language :: Python :: 3
Classifier: Programming Language :: Python :: 3.12
Classifier: Programming Language :: Python :: 3.13
License-File: LICENSE
